birdseye_mc/__main__.py
birdseye_mc/dynmap/__init__.py
birdseye_mc/dynmap/api/__init__.py
birdseye_mc/dynmap/api/configuration.py
birdseye_mc/dynmap/api/faces.py
birdseye_mc/dynmap/api/tiles.py
birdseye_mc/dynmap/api/update.py
birdseye_mc/dynmap/exceptions/__init__.py
birdseye_mc/dynmap/exceptions/invalid_endpoint_exception.py
birdseye_mc/dynmap/models/__init__.py
birdseye_mc/dynmap/models/configuration.py
birdseye_mc/dynmap/models/player.py
birdseye_mc/dynmap/models/update.py
birdseye_mc/dynmap/models/world.py
birdseye_mc/ui/__init__.py
birdseye_mc/ui/window.py
birdseye_mc-0.1.1.dist-info/entry_points.txt
birdseye_mc-0.1.1.dist-info/LICENSE
birdseye_mc-0.1.1.dist-info/WHEEL
birdseye_mc-0.1.1.dist-info/METADATA
birdseye_mc-0.1.1.dist-info/RECORD
